mawaqit_astro/__init__.py
mawaqit_astro/exceptions.py
mawaqit_astro/types.py
mawaqit_astro/core/__init__.py
mawaqit_astro/core/almanac.py
mawaqit_astro/core/aries.py
mawaqit_astro/core/measures.py
mawaqit_astro/core/moon.py
mawaqit_astro/core/nutation.py
mawaqit_astro/core/polaris.py
mawaqit_astro/core/sun.py
mawaqit_astro/core/utils.py
mawaqit_astro/core/weekday.py
mawaqit_astro/prayers/__init__.py
mawaqit_astro/prayers/asr.py
mawaqit_astro/prayers/base.py
mawaqit_astro/prayers/calculator.py
mawaqit_astro/prayers/dhuhr.py
mawaqit_astro/prayers/fajr.py
mawaqit_astro/prayers/isha.py
mawaqit_astro/prayers/maghrib.py
mawaqit_astro/prayers/methods.py
mawaqit_astro/prayers/sunrise.py
mawaqit_astro-1.0.2.dist-info/licenses/LICENSE
mawaqit_astro-1.0.2.dist-info/METADATA
mawaqit_astro-1.0.2.dist-info/WHEEL
mawaqit_astro-1.0.2.dist-info/top_level.txt
mawaqit_astro-1.0.2.dist-info/RECORD
