Metadata-Version: 2.4
Name: mawaqit-astro
Version: 1.0.2
Summary: A comprehensive Python library for astronomical calculations and prayer times.
Author-email: Mawaqit Team <ghulamhasnain.pro@gmail.com>
Project-URL: Homepage, https://github.com/h-ghulam-hasnain/mawaqit
Project-URL: Bug Tracker, https://github.com/h-ghulam-hasnain/mawaqit/issues
Keywords: astronomy,prayer-times,salat,islam,sun,moon
Classifier: Programming Language :: Python :: 3
Classifier: License :: OSI Approved :: MIT License
Classifier: Operating System :: OS Independent
Classifier: Intended Audience :: Developers
Classifier: Topic :: Scientific/Engineering :: Astronomy
Requires-Python: >=3.7
License-File: LICENSE
Dynamic: license-file
